<?xml version="1.0" encoding="utf-8" ?><dwsync><file name="miniLogoTwo.png" server="ftp.onstatic-it.setupdns.net" local="3571733590" remote="3589486380" Dst="-1" /><file name="mainLogoTwo.png" server="ftp.onstatic-it.setupdns.net" local="3571733618" remote="3589486380" Dst="-1" /><file name="photoOne.jpg" server="ftp.onstatic-it.setupdns.net" local="3570627694" remote="3589486380" Dst="-1" /><file name="photoFour.jpg" server="ftp.onstatic-it.setupdns.net" local="3570627656" remote="3589486380" Dst="-1" /><file name="photoThree.jpg" server="ftp.onstatic-it.setupdns.net" local="3570627740" remote="3589486380" Dst="-1" /><file name="PhotoTwo.jpg" server="ftp.onstatic-it.setupdns.net" local="3570627764" remote="3589485780" Dst="-1" /><file name="upIconTwo.png" server="ftp.onstatic-it.setupdns.net" local="3571733539" remote="3589486380" Dst="-1" /><file name=".DS_Store" server="ftp.onstatic-it.setupdns.net" local="3577075925" remote="3589486380" Dst="-1" /><file name="photoTwo.jpg" server="ftp.onstatic-it.setupdns.net" local="3570627764" remote="3589486380" Dst="-1" /></dwsync>